Metadata-Version: 2.1
Name: messenger-GB-client-acronics-31012023
Version: 1
Summary: Client package
Author: Michail Paramonov
Author-email: test@mail.ru
